{"movie_ghost": {"Poster": "https://images-na.ssl-images-amazon.com/images/M/MV5BMTU0NzQzODUzNl5BMl5BanBnXkFtZTgwMjc5NTYxMTE@._V1_SX300.jpg", "imdbVotes": "160,136", "Plot": "After a young man is murdered, his spirit stays behind to warn his lover of impending danger, with the help of a reluctant psychic.", "Director": "Jerry Zucker", "Awards": "Won 2 Oscars. Another 16 wins & 22 nominations.", "Ratings": [{"Value": "7.0/10", "Source": "Internet Movie Database"}, {"Value": "74%", "Source": "Rotten Tomatoes"}, {"Value": "52/100", "Source": "Metacritic"}], "Title": "Ghost", "DVD": "24 Apr 2001", "Released": "13 Jul 1990", "Genre": "Drama, Fantasy, Romance", "Production": "Paramount Pictures", "BoxOffice": "N/A", "imdbRating": "7.0", "imdbID": "tt0099653", "Rated": "PG-13", "Type": "movie", "Language": "English", "Actors": "Patrick Swayze, Demi Moore, Whoopi Goldberg, Tony Goldwyn", "Metascore": "52", "Year": "1990", "Country": "USA", "Website": "N/A", "Response": "True", "Runtime": "127 min", "Writer": "Bruce Joel Rubin"}, "twitter_user_Jerry Zucker": [{"is_quote_status": false, "created_at": "Sun Feb 19 18:10:49 +0000 2017", "text": "Use python to make a post. See if it works!", "in_reply_to_status_id_str": null, "favorite_count": 2, "truncated": false, "retweet_count": 0, "id": 833378320117018625, "in_reply_to_screen_name": null, "retweeted": false, "contributors": null, "place": null, "favorited": false, "user": {"verified": false, "default_profile": true, "contributors_enabled": false, "follow_request_sent": false, "entities": {"description": {"urls": []}}, "profile_link_color": "1DA1F2", "description": "", "favourites_count": 0, "url": null, "id": 833369294885023750, "name": "Shuyuan Xiao", "is_translator": false, "profile_background_tile": false, "profile_sidebar_fill_color": "DDEEF6", "profile_image_url": "http://abs.twimg.com/sticky/default_profile_images/default_profile_normal.png", "is_translation_enabled": false, "listed_count": 0, "statuses_count": 1, "utc_offset": null, "protected": false, "id_str": "833369294885023750", "lang": "en", "profile_image_url_https": "https://abs.twimg.com/sticky/default_profile_images/default_profile_normal.png", "profile_sidebar_border_color": "C0DEED", "default_profile_image": true, "profile_background_image_url": null, "profile_text_color": "333333", "translator_type": "none", "location": "", "has_extended_profile": false, "notifications": false, "friends_count": 21, "time_zone": null, "profile_background_color": "F5F8FA", "screen_name": "shuyuan99", "created_at": "Sun Feb 19 17:34:57 +0000 2017", "profile_background_image_url_https": null, "profile_use_background_image": true, "geo_enabled": false, "followers_count": 1, "following": false}, "id_str": "833378320117018625", "entities": {"hashtags": [], "symbols": [], "urls": [], "user_mentions": []}, "source": "<a href=\"http://programsinformationpeople.org\" rel=\"nofollow\">shuyuanx</a>", "in_reply_to_user_id": null, "in_reply_to_status_id": null, "geo": null, "lang": "en", "coordinates": null, "in_reply_to_user_id_str": null}]}